Metadata-Version: 2.1
Name: bmaquet-tap-jira
Version: 1.0.4
Summary: Singer.io tap for extracting data from the Jira API
Home-page: http://singer.io
Author: Stitch
License: UNKNOWN
Platform: UNKNOWN
Classifier: Programming Language :: Python :: 3 :: Only
Provides-Extra: dev
License-File: LICENSE
